setup.cfg
setup.py
bigben/__init__.py
bigben/client.py
bigben/errors.py
bigben_python_lib.egg-info/PKG-INFO
bigben_python_lib.egg-info/SOURCES.txt
bigben_python_lib.egg-info/dependency_links.txt
bigben_python_lib.egg-info/top_level.txt
tests/__init__.py
tests/client_tests.py
tests/errors_tests.py