Metadata-Version: 1.1
Name: bigben-python-lib
Version: 0.0.5
Summary: Client library used for interacting with BigBen APIs.
Home-page: https://github.com/sgiroux/bigben-python-lib
Author: Sam Giroux
Author-email: giroux@gmail.com
License: MIT
Keywords: BigBen
Platform: UNKNOWN
Classifier: Development Status :: 4 - Beta
Classifier: Intended Audience :: Developers
Classifier: Topic :: Software Development :: Libraries :: Python Modules
Classifier: License :: OSI Approved :: MIT License
Classifier: Programming Language :: Python :: 2.6
Classifier: Programming Language :: Python :: 2.7
Classifier: Programming Language :: Python :: 3
Classifier: Programming Language :: Python :: 3.2
Classifier: Programming Language :: Python :: 3.3
Classifier: Programming Language :: Python :: 3.4
